magiconf/__init__.py
magiconf/env.py
magiconf/errors.py
magiconf/flags.py
magiconf/types.py
magiconf-0.1.3.dist-info/WHEEL
magiconf-0.1.3.dist-info/METADATA
magiconf-0.1.3.dist-info/RECORD
