Metadata-Version: 2.1
Name: magiconf
Version: 0.1.3
Summary: A small library to automagically load and parse configuration from either environment, configuration file or command line arguments.
License: MIT
Author: Vladimir Kotikov
Author-email: kotikov.vladimir@gmail.com
Requires-Python: >=3.7,<4.0
Classifier: License :: OSI Approved :: MIT License
Classifier: Programming Language :: Python :: 3
Classifier: Programming Language :: Python :: 3.7
Classifier: Programming Language :: Python :: 3.8
